argdown/__init__.py
argdown/argdown.py
argdown-0.0.1.dist-info/DESCRIPTION.rst
argdown-0.0.1.dist-info/METADATA
argdown-0.0.1.dist-info/RECORD
argdown-0.0.1.dist-info/WHEEL
argdown-0.0.1.dist-info/entry_points.txt
argdown-0.0.1.dist-info/metadata.json
argdown-0.0.1.dist-info/top_level.txt
