Metadata-Version: 2.0
Name: argdown
Version: 0.0.1
Summary: Markdown export for the argparse module
Home-page: https://github.com/9999years/argdown
Author: Rebecca Turner
Author-email: UNKNOWN
License: MIT
Keywords: markdown argparse
Platform: UNKNOWN
Classifier: Development Status :: 3 - Alpha
Classifier: Intended Audience :: Developers
Classifier: Environment :: Console
Classifier: License :: OSI Approved :: MIT License
Classifier: Programming Language :: Python :: 3.6
Classifier: Operating System :: OS Independent
Classifier: Topic :: Text Processing :: Markup
